VRAresultTests/Racial_Block_Voting_tools.py
VRAresultTests/__init__.py
VRAresultTests/rpvVoterIndex.py
VRAresultsTest-0.1.0.dist-info/LICENSE.txt
VRAresultsTest-0.1.0.dist-info/METADATA
VRAresultsTest-0.1.0.dist-info/WHEEL
VRAresultsTest-0.1.0.dist-info/top_level.txt
VRAresultsTest-0.1.0.dist-info/RECORD
